mmselfsup/__init__.py
mmselfsup/registry.py
mmselfsup/version.py
mmselfsup/.mim/model-index.yml
mmselfsup/.mim/configs/benchmarks/classification/knn_imagenet.py
mmselfsup/.mim/configs/benchmarks/classification/svm_voc07.py
mmselfsup/.mim/configs/benchmarks/classification/_base_/datasets/imagenet.py
mmselfsup/.mim/configs/benchmarks/classification/_base_/datasets/imagenet_swin_192.py
mmselfsup/.mim/configs/benchmarks/classification/_base_/datasets/inaturalist2018.py
mmselfsup/.mim/configs/benchmarks/classification/_base_/datasets/places205.py
mmselfsup/.mim/configs/benchmarks/classification/_base_/datasets/pipelines/rand_aug.py
mmselfsup/.mim/configs/benchmarks/classification/_base_/models/resnet50.py
mmselfsup/.mim/configs/benchmarks/classification/_base_/models/resnet50_multihead.py
mmselfsup/.mim/configs/benchmarks/classification/_base_/models/vit-small-p16.py
mmselfsup/.mim/configs/benchmarks/classification/_base_/schedules/adamw_coslr-100e_in1k.py
mmselfsup/.mim/configs/benchmarks/classification/_base_/schedules/lars_coslr-90e.py
mmselfsup/.mim/configs/benchmarks/classification/_base_/schedules/sgd_coslr-100e.py
mmselfsup/.mim/configs/benchmarks/classification/_base_/schedules/sgd_steplr-100e.py
mmselfsup/.mim/configs/benchmarks/classification/cifar/resnet50_8xb128-steplr-350e_cifar10.py
mmselfsup/.mim/configs/benchmarks/classification/imagenet/resnet50-sobel_linear-8xb32-steplr-100e_in1k.py
mmselfsup/.mim/configs/benchmarks/classification/imagenet/resnet50-sobel_mhead_linear-8xb32-steplr-90e_in1k.py
mmselfsup/.mim/configs/benchmarks/classification/imagenet/resnet50_8xb32-steplr-90e_in1k.py
mmselfsup/.mim/configs/benchmarks/classification/imagenet/resnet50_linear-8xb128-coslr-90e_in1k.py
mmselfsup/.mim/configs/benchmarks/classification/imagenet/resnet50_linear-8xb32-coslr-100e_in1k.py
mmselfsup/.mim/configs/benchmarks/classification/imagenet/resnet50_linear-8xb32-steplr-100e_in1k.py
mmselfsup-1.0.0.dist-info/LICENSE
mmselfsup-1.0.0.dist-info/METADATA
mmselfsup-1.0.0.dist-info/WHEEL
mmselfsup-1.0.0.dist-info/top_level.txt
mmselfsup-1.0.0.dist-info/RECORD
